<?xml version="1.0" encoding="UTF-8"?>

<ProjectSettings>
  <Name value="Reach"/>
  <Version value="1.2.0"/>
  <Description value="Creative Reverb Plugin"/>
  <BundleIdentifier value="com.sinuslabs.reach"/>
  <PluginCode value="Reac"/>
  <EmbedAudioFiles value="1"/>
  <EmbedImageFiles value="1"/>
  <SupportFullDynamicsHLAC value="No"/>
  <AdditionalDspLibraries value=""/>
  <OSXStaticLibs value=""/>
  <WindowsStaticLibFolder value=""/>
  <ExtraDefinitionsWindows value="ENABLE_ALL_PEAK_METERS=1"/>
  <ExtraDefinitionsOSX value="ENABLE_ALL_PEAK_METERS=1"/>
  <ExtraDefinitionsIOS value="ENABLE_ALL_PEAK_METERS=1"/>
  <ExtraDefinitionsLinux value="ENABLE_ALL_PEAK_METERS=1"/>
  <AppGroupID value=""/>
  <RedirectSampleFolder value=""/>
  <AAXCategoryFX value="AAX_ePlugInCategory_Modulation"/>
  <SupportMonoFX value="No"/>
  <EnableMidiInputFX value="No"/>
  <EnableSoundGeneratorsFX value="No"/>
  <VST3Support value="1"/>
  <UseRawFrontend value="No"/>
  <ExpansionType value="Disabled"/>
  <EncryptionKey value=""/>
  <LinkExpansionsToProject value="No"/>
  <ReadOnlyFactoryPresets value="No"/>
  <ForceStereoOutput value="No"/>
  <EnableMidiOut value="No"/>
  <AdminPermissions value="No"/>
</ProjectSettings>
