<?xml version="1.0" encoding="UTF-8"?>

<ContentProperties DeviceType="Desktop">
  <Component type="ScriptPanel" id="panel_background" x="0.0" y="0.0" itemColour="4293717228"
             itemColour2="4292072403" width="1134.0" height="516.0">
    <Component type="ScriptPanel" id="panel_backdrop" x="14.0" y="68.0" width="1106.0"
               height="428.0" parentComponent="panel_background" itemColour2="4278190080"
               itemColour="4278190080" text="backgrop" borderRadius="5.0" bgColour="16711680"
               textColour="4278190080"/>
    <Component type="ScriptPanel" id="panel_header" x="0.0" y="6.0" width="1140.0"
               height="60.0" parentComponent="panel_background" itemColour="0"
               itemColour2="0" bgColour="16777215" textColour="16777215">
      <Component type="ScriptSlider" id="header_vumeter_ch1" x="868.0" y="32.0"
                 width="162.0" height="6.0" max="1.100000023841858" parentComponent="panel_header"
                 style="Horizontal" showTextBox="0" scrollWheel="0" enabled="0"
                 itemColour2="0" itemColour="4293125091" bgColour="4284835173"
                 saveInPreset="0"/>
      <Component type="ScriptSlider" id="header_vumeter_ch2" x="868.0" y="26.0"
                 width="162.0" height="6.0" max="1.100000023841858" parentComponent="panel_header"
                 style="Horizontal" showTextBox="0" itemColour2="0" itemColour="4293125091"
                 bgColour="4284835173" enabled="0" saveInPreset="0"/>
      <Component type="ScriptButton" id="button_title" x="0.0" y="-6.0" width="140.0"
                 height="70.0" text=" REACH" parentComponent="panel_header" saveInPreset="0"/>
      <Component type="ScriptButton" id="button_logo" x="1080.0" y="4.0" width="40.0"
                 height="50.0" parentComponent="panel_header" text="logo" scaleFactor="2.0"
                 bgColour="4278190080" itemColour="4283387727" saveInPreset="0"/>
      <Component type="ScriptButton" id="button_preset_leftArrow" x="150.0" y="14.0"
                 parentComponent="panel_header" width="20.0" height="30.0" text="leftArrow"
                 saveInPreset="0" bgColour="4286874756" itemColour="4281545523"
                 itemColour2="4285229931" isMomentary="1"/>
      <Component type="ScriptButton" id="button_preset_rightArrow" x="170.3999938964844"
                 y="14.0" parentComponent="panel_header" text="rightArrow" width="20.0"
                 height="30.0" saveInPreset="0" itemColour="4281545523" bgColour="4286874756"
                 textColour="4285229931" itemColour2="4285229931" isMomentary="1"/>
      <Component type="ScriptLabel" id="themeAble_label_out" x="790.0" y="24.20000076293945"
                 parentComponent="panel_header" fontName="inter-semi" text="MAIN OUT"
                 textColour="-1842205" fontSize="12.0" height="16.79999923706055"
                 editable="0" itemColour2="0" width="76.80000305175781"/>
      <Component type="ScriptButton" id="button_presetBrowser" x="200.0" y="4.0"
                 parentComponent="panel_header" width="200.0" height="50.0" text="- INIT -"
                 textColour="272841017" itemColour2="0" itemColour="268435456"
                 bgColour="16711680" saveInPreset="0" enableMidiLearn="0"/>
      <Component type="ScriptButton" id="onPresetLoad" x="330.0" y="24.0" parentComponent="panel_header"
                 text="" visible="0" width="76.80000305175781" height="16.79999923706055"/>
      <Component type="ScriptButton" id="button_quickTheme" x="1050.0" y="24.0"
                 parentComponent="panel_header" width="15.0" height="15.0" text="icon-halfCircle"
                 isMomentary="1" itemColour="1727987712"/>
    </Component>
    <Component type="ScriptPanel" id="themeablePanel_reverb" x="18.0" y="72.0"
               width="288.0" height="420.0" parentComponent="panel_background"
               itemColour="4292730333" itemColour2="4292927712" textColour="4289045925"
               borderRadius="5.0">
      <Component type="ScriptSlider" id="knob_reverb_space" x="162.0" y="36.0"
                 parentComponent="themeablePanel_reverb" width="70.0" height="100.0"
                 itemColour="3355443" itemColour2="1118481" textColour="16777215"
                 bgColour="16777215" text="SPACE" showTextBox="0" macroControl="No MacroControl"
                 scaleFactor="0.5" mouseSensitivity="2.0" isPluginParameter="1"
                 pluginParameterName="Space" max="5.0" mode="NormalizedPercentage"
                 enableMidiLearn="0" defaultValue="1.0"/>
      <Component type="ScriptSlider" id="knob_reverb_diffusion" x="48.0" y="150.0"
                 textColour="16777215" itemColour2="1118481" itemColour="3355443"
                 bgColour="16777215" showTextBox="0" text="DIFFUSION" width="70.0"
                 height="100.0" parentComponent="themeablePanel_reverb" macroControl="No MacroControl"
                 scaleFactor="0.5" mouseSensitivity="2.0" isPluginParameter="1"
                 pluginParameterName="Diffusion" mode="NormalizedPercentage" suffix="%"
                 middlePosition="0.5" enableMidiLearn="0" defaultValue="1.0"/>
      <Component type="ScriptSlider" id="knob_reverb_damping" x="162.0" y="150.0"
                 width="70.0" height="100.0" itemColour="3355443" textColour="16777215"
                 showTextBox="0" itemColour2="1118481" text="DAMPING" parentComponent="themeablePanel_reverb"
                 macroControl="No MacroControl" scaleFactor="0.5" mouseSensitivity="2.0"
                 isPluginParameter="1" pluginParameterName="Damping" mode="NormalizedPercentage"
                 suffix="%" middlePosition="0.5" enableMidiLearn="0" defaultValue="0.5"/>
      <Component type="ScriptSlider" id="knob_reverb_mix" x="96.0" y="270.0" width="100.0"
                 height="150.0" text="Reverb MIX" showTextBox="0" textColour="16777215"
                 itemColour2="1118481" itemColour="3355443" bgColour="16777215"
                 parentComponent="themeablePanel_reverb" macroControl="No MacroControl"
                 scaleFactor="0.6000000238418579" mouseSensitivity="3.0" isPluginParameter="1"
                 pluginParameterName="Reverb Mix" mode="NormalizedPercentage"
                 suffix="%" middlePosition="0.5" processorId="Effect Slot1_Hardcoded Master FX"
                 enableMidiLearn="0" defaultValue="0.5"/>
      <Component type="ScriptLabel" id="themeAble_label_panel_reverb" x="0.0"
                 y="0.0" parentComponent="themeablePanel_reverb" text="REVERB"
                 fontSize="16.0" fontName="inter-semi" textColour="-1842205" editable="0"
                 itemColour2="0" width="80.0" height="30.0"/>
      <Component type="ScriptSlider" id="knob_reverb_time" x="48.0" y="36.0" parentComponent="themeablePanel_reverb"
                 width="70.0" height="100.0" mouseSensitivity="2.0" max="12.0"
                 middlePosition="6.0" suffix=" ms" pluginParameterName="Time"
                 isPluginParameter="1" text="TIME" enableMidiLearn="0" defaultValue="1.0"/>
    </Component>
    <Component type="ScriptPanel" id="themeablePanel_cleanup" x="576.0" y="330.0"
               width="246.0" height="162.0" parentComponent="panel_background"
               itemColour="4292730333" itemColour2="4293322470" textColour="4289045925"
               borderRadius="5.0">
      <Component type="ScriptSlider" id="knob_cleanup_ducking" x="34.0" y="40.0"
                 width="70.0" height="100.0" text="DUCKING" mode="NormalizedPercentage"
                 suffix="%" middlePosition="0.5" parentComponent="themeablePanel_cleanup"
                 mouseSensitivity="2.0" isPluginParameter="1" pluginParameterName="Ducking"
                 enableMidiLearn="0"/>
      <Component type="ScriptSlider" id="knob_cleanup_preDelay" x="144.0" y="40.0"
                 width="70.0" height="100.0" text="PRE DELAY" mode="Time" max="10000.0"
                 suffix=" ms" middlePosition="1000.0" parentComponent="themeablePanel_cleanup"
                 mouseSensitivity="2.0" isPluginParameter="1" pluginParameterName="Pre Delay"
                 enableMidiLearn="0"/>
      <Component type="ScriptLabel" id="themeAble_label_panel_reverberation" x="0.0"
                 y="0.0" text="CLEANUP" fontName="inter-semi" width="90.0" height="30.0"
                 fontSize="16.0" textColour="-1842205" parentComponent="themeablePanel_cleanup"
                 editable="0" itemColour2="0"/>
    </Component>
    <Component type="ScriptPanel" id="themeablePanel_modulation" x="312.0" y="330.0"
               width="258.0" height="162.0" parentComponent="panel_background"
               itemColour="4292730333" itemColour2="4293125091" textColour="4289045925"
               borderRadius="5.0">
      <Component type="ScriptSlider" id="knob_modulation_depth" x="36.0" y="36.0"
                 width="70.0" height="100.0" mouseSensitivity="2.0" isPluginParameter="1"
                 pluginParameterName="Mod Depth" parentComponent="themeablePanel_modulation"
                 text="DEPTH" mode="NormalizedPercentage" suffix="%" middlePosition="0.5"
                 enableMidiLearn="0"/>
      <Component type="ScriptSlider" id="knob_modulation_frequency" x="144.0"
                 y="36.0" width="70.0" height="100.0" mouseSensitivity="2.0" max="10.0"
                 suffix=" Hz" middlePosition="5.0" pluginParameterName="Mod Frequency"
                 isPluginParameter="1" parentComponent="themeablePanel_modulation"
                 text="RATE" enableMidiLearn="0"/>
      <Component type="ScriptLabel" id="themeAble_label_panel_flair" x="0.0" y="0.0"
                 text="MODULATION" fontName="inter-semi" fontSize="16.0" textColour="-1842205"
                 parentComponent="themeablePanel_modulation" editable="0" itemColour2="0"
                 width="120.0" height="30.0"/>
    </Component>
    <Component type="ScriptPanel" id="themeablePanel_effects" x="828.0" y="72.0"
               width="288.0" height="252.0" parentComponent="panel_background"
               itemColour="4292730333" itemColour2="4293059298" textColour="4289045925"
               borderRadius="5.0">
      <Component type="ScriptLabel" id="themeAble_label_panel_effects" x="0.0"
                 y="0.0" fontSize="16.0" fontName="inter-semi" text="EFFECTS"
                 textColour="-1842205" parentComponent="themeablePanel_effects"
                 width="80.0" height="30.0" editable="0" itemColour2="0"/>
      <Component type="ScriptButton" id="button_degrade_bypass" x="36.0" y="36.0"
                 width="10.0" height="10.0" parentComponent="themeablePanel_effects"/>
      <Component type="ScriptPanel" id="containerPanel_degrade" x="42.0" y="38.0"
                 width="90.0" height="100.0" parentComponent="themeablePanel_effects"
                 itemColour2="0" itemColour="0" bgColour="16777215" textColour="16777215">
        <Component type="ScriptSlider" id="knob_effects_degrade" x="10.0" y="0.0"
                   width="70.0" height="100.0" text="Degrade" parentComponent="containerPanel_degrade"
                   mouseSensitivity="2.0" pluginParameterName="Degrade Mix" isPluginParameter="1"
                   mode="NormalizedPercentage" suffix="%" middlePosition="0.5" enableMidiLearn="0"/>
      </Component>
      <Component type="ScriptButton" id="button_flanger_bypass" x="156.0" y="36.0"
                 width="10.0" height="10.0" parentComponent="themeablePanel_effects"/>
      <Component type="ScriptPanel" id="containerPanel_flanger" x="162.0" y="28.0"
                 width="90.0" height="110.0" itemColour="0" itemColour2="0" textColour="16777215"
                 bgColour="16777215" parentComponent="themeablePanel_effects">
        <Component type="ScriptSlider" id="knob_effects_flair" x="10.0" y="10.0"
                   width="70.0" height="100.0" text="Flanger" parentComponent="containerPanel_flanger"
                   mouseSensitivity="2.0" pluginParameterName="Flanger Mix" isPluginParameter="1"
                   mode="NormalizedPercentage" suffix="%" middlePosition="0.5" enableMidiLearn="0"/>
      </Component>
      <Component type="ScriptButton" id="button_chorus_bypass" x="36.0" y="147.0"
                 width="10.0" height="10.0" parentComponent="themeablePanel_effects"/>
      <Component type="ScriptPanel" id="containerPanel_chorus" x="42.0" y="138.0"
                 bgColour="16777215" itemColour="0" itemColour2="0" textColour="16777215"
                 width="90.0" height="110.0" parentComponent="themeablePanel_effects">
        <Component type="ScriptSlider" id="knob_effects_chorus" x="10.0" y="8.0"
                   text="Chorus" width="70.0" height="100.0" parentComponent="containerPanel_chorus"
                   mouseSensitivity="2.0" pluginParameterName="Chorus Mix" isPluginParameter="1"
                   mode="NormalizedPercentage" suffix="%" middlePosition="0.5" enableMidiLearn="0"/>
      </Component>
      <Component type="ScriptButton" id="button_distort_bypass" x="156.0" y="147.0"
                 width="10.0" height="10.0" parentComponent="themeablePanel_effects"/>
      <Component type="ScriptPanel" id="containerPanel_distort" x="162.0" y="138.0"
                 width="90.0" height="110.0" textColour="16777215" itemColour2="0"
                 itemColour="0" bgColour="16777215" parentComponent="themeablePanel_effects">
        <Component type="ScriptSlider" id="knob_effects_distortion" x="10.0" y="8.0"
                   width="70.0" height="100.0" parentComponent="containerPanel_distort"
                   mouseSensitivity="2.0" pluginParameterName="Distortion Mix" isPluginParameter="1"
                   text="Distort" mode="NormalizedPercentage" suffix="%" middlePosition="0.5"
                   enableMidiLearn="0"/>
      </Component>
    </Component>
    <Component type="ScriptPanel" id="themeablePanel_io" x="828.0" y="330.0"
               width="288.0" height="162.0" itemColour="4292730333" itemColour2="4292730333"
               textColour="4289045925" parentComponent="panel_background" borderRadius="5.0">
      <Component type="ScriptSlider" id="knob_io_in" x="52.0" y="50.0" text="GAIN"
                 width="60.0" height="90.0" textColour="16777215" itemColour2="1118481"
                 itemColour="3355443" bgColour="16777215" parentComponent="themeablePanel_io"
                 scaleFactor="0.4000000059604645" mode="Decibel" min="-100.0"
                 max="30.0" stepSize="0.1000000014901161" suffix=" dB" middlePosition="0.0"
                 mouseSensitivity="4.0" isPluginParameter="1" pluginParameterName="Gain"
                 enableMidiLearn="0"/>
      <Component type="ScriptSlider" id="knob_io_out" x="152.0" y="15.0" width="110.0"
                 height="140.0" bgColour="16777215" itemColour="3355443" itemColour2="1118481"
                 textColour="16777215" text="IO MIX" parentComponent="themeablePanel_io"
                 numStrips="128.0" scaleFactor="0.5" suffix="%" middlePosition="0.5"
                 mouseSensitivity="3.0" isPluginParameter="1" pluginParameterName="Mix"
                 mode="NormalizedPercentage" enableMidiLearn="0" defaultValue="0.5"/>
      <Component type="ScriptLabel" id="themeAble_label_io" x="0.0" y="0.0" parentComponent="themeablePanel_io"
                 width="80.0" height="30.0" textColour="-1842205" fontSize="16.0"
                 text="MASTER" editable="0" fontName="inter-semi" itemColour2="0"/>
    </Component>
    <Component type="ScriptPanel" id="panelDisplay_display" x="312.0" y="72.0"
               width="510.0" height="252.0" itemColour="0" itemColour2="4278650631"
               parentComponent="panel_background" textColour="0">
      <Component type="ScriptPanel" id="display_main" x="0.0" y="0.0" width="510.0"
                 height="252.0" parentComponent="panelDisplay_display" textColour="16777215"
                 bgColour="16777215" itemColour="0" itemColour2="0" visible="0">
        <Component type="ScriptPanel" id="displayPanel_fx1" x="8.0" y="208.0" width="60.0"
                   height="35.0" text="Reverb" parentComponent="display_main"/>
        <Component type="ScriptPanel" id="displayPanel_fx2" x="78.0" y="208.0" width="60.0"
                   height="35.0" text="Degrade" parentComponent="display_main"/>
        <Component type="ScriptPanel" id="displayPanel_fx3" x="148.0" y="208.0"
                   width="60.0" height="35.0" text="Flanger" parentComponent="display_main"/>
        <Component type="ScriptPanel" id="displayPanel_fx4" x="218.0" y="208.0"
                   width="60.0" height="35.0" text="Chorus" parentComponent="display_main"/>
        <Component type="ScriptPanel" id="displayPanel_fx5" x="288.0" y="208.0"
                   width="60.0" text="Distort" height="35.0" parentComponent="display_main"/>
        <Component type="ScriptPanel" id="display_main_reverb" x="0.0" y="0.0" parentComponent="display_main"
                   width="510.0" height="198.0" itemColour2="0" itemColour="0" bgColour="16777215"
                   textColour="16777215" visible="0">
          <Component type="ScriptPanel" id="panel_animation_reverb" x="180.0" y="30.0"
                     parentComponent="display_main_reverb" width="150.0" height="150.0"/>
        </Component>
        <Component type="ScriptPanel" id="display_main_chorus" x="0.0" y="0.0" width="510.0"
                   height="198.0" parentComponent="display_main" textColour="16777215"
                   visible="0">
          <Component type="ScriptPanel" id="panel_animation_chorus" x="180.0" y="30.0"
                     width="150.0" height="150.0" parentComponent="display_main_chorus"/>
        </Component>
        <Component type="ScriptPanel" id="display_main_distortion" x="0.0" y="0.0"
                   width="510.0" height="200.0" parentComponent="display_main" bgColour="16769505"
                   textColour="16777215" visible="0">
          <Component type="ScriptPanel" id="panel_animation_distortion" x="180.0"
                     y="30.0" width="150.0" height="150.0" parentComponent="display_main_distortion"/>
        </Component>
        <Component type="ScriptPanel" id="display_main_waveform" x="0.0" y="0.0"
                   width="510.0" height="198.0" parentComponent="display_main" itemColour="0"
                   itemColour2="0" bgColour="16777215" textColour="0" visible="0">
          <Component type="ScriptFloatingTile" id="FloatingTile1" x="8.0" y="38.79999923706055"
                     width="490.0" height="160.0" ContentType="AudioAnalyser" bgColour="16769505"
                     itemColour="4294967295" itemColour2="16711680" textColour="4294901760"
                     Data="{&#10;  &quot;ProcessorId&quot;: &quot;Analyser1&quot;,&#10;  &quot;Index&quot;: 1,&#10;  &quot;FollowWorkspace&quot;: false&#10;}"
                     parentComponent="display_main_waveform" updateAfterInit="0"/>
        </Component>
        <Component type="ScriptPanel" id="display_main_degrade" x="0.0" y="0.0"
                   width="510.0" height="198.0" parentComponent="display_main" itemColour2="16711680"
                   itemColour="0" bgColour="16777215" textColour="16777215" visible="0">
          <Component type="ScriptPanel" id="panel_animation_degrade" x="180.0" y="30.0"
                     width="150.0" height="150.0" parentComponent="display_main_degrade"/>
        </Component>
        <Component type="ScriptPanel" id="display_main_flair" x="0.0" y="0.0" width="510.0"
                   height="198.0" parentComponent="display_main" itemColour2="3538688"
                   itemColour="65315" bgColour="16777215" textColour="16777215"
                   visible="0">
          <Component type="ScriptPanel" id="panel_animation_flair1" x="135.0" y="30.0"
                     width="240.0" height="160.0" parentComponent="display_main_flair"/>
        </Component>
        <Component type="ScriptButton" id="button_not_activated" x="358.0" y="8.0"
                   parentComponent="display_main" width="140.0" height="30.0" isMomentary="1"
                   text="NOT ACTIVATED" enableMidiLearn="0" visible="0"/>
      </Component>
      <Component type="ScriptPanel" id="display_effects" x="0.0" y="0.0" parentComponent="panelDisplay_display"
                 width="510.0" height="252.0" itemColour="4278190080" itemColour2="4278190080"
                 textColour="16777215">
        <Component type="ScriptPanel" id="panel_effectCustomizer" x="8.0" y="8.0"
                   width="500.0" height="230.0" itemColour2="4278190080" itemColour="4278190080"
                   bgColour="16777215" parentComponent="display_effects" textColour="16777215">
          <Component type="ScriptPanel" id="panel_customizerHeader" x="0.0" y="0.0"
                     width="495.0" height="40.0" parentComponent="panel_effectCustomizer"
                     textColour="16777215">
            <Component type="ScriptPanel" id="panel_slotArea1" x="1.200000047683716"
                       y="6.0" parentComponent="panel_customizerHeader" width="96.0"
                       height="30.0" itemColour="4294901760" visible="0"/>
            <Component type="ScriptPanel" id="panel_slotArea2" x="98.40000152587891"
                       y="6.0" parentComponent="panel_customizerHeader" width="96.0"
                       itemColour="4278255378" visible="0" height="30.0"/>
            <Component type="ScriptPanel" id="panel_slotArea3" x="195.6000061035156"
                       y="6.0" width="96.0" itemColour="4278228479" parentComponent="panel_customizerHeader"
                       visible="0" height="30.0"/>
            <Component type="ScriptPanel" id="panel_slotArea4" x="292.7999877929688"
                       y="6.0" width="96.0" itemColour="4294901866" parentComponent="panel_customizerHeader"
                       visible="0" height="30.0"/>
            <Component type="ScriptPanel" id="panel_slotArea5" x="388.7999877929688"
                       y="6.0" itemColour="4294967040" width="96.0" parentComponent="panel_customizerHeader"
                       visible="0" height="30.0"/>
            <Component type="ScriptPanel" id="panel_effectTab1" x="-0.2999999523162842"
                       y="0.0" width="99.0" height="40.0" parentComponent="panel_customizerHeader"
                       allowDragging="1" allowCallbacks="Clicks, Hover &amp; Dragging"
                       itemColour="4278239743" text="Reverb"/>
            <Component type="ScriptPanel" id="panel_effectTab2" x="96.90000152587891"
                       y="0.0" width="99.0" height="40.0" parentComponent="panel_customizerHeader"
                       allowDragging="1" allowCallbacks="Clicks, Hover &amp; Dragging"
                       itemColour="4278239743" text="Degrade"/>
            <Component type="ScriptPanel" id="panel_effectTab3" x="194.1000061035156"
                       y="0.0" width="99.0" height="40.0" parentComponent="panel_customizerHeader"
                       allowDragging="1" allowCallbacks="Clicks, Hover &amp; Dragging"
                       itemColour="4278239743" text="Flanger"/>
            <Component type="ScriptPanel" id="panel_effectTab4" x="291.2999877929688"
                       y="0.0" parentComponent="panel_customizerHeader" width="99.0"
                       height="40.0" allowDragging="1" allowCallbacks="Clicks, Hover &amp; Dragging"
                       itemColour="4278239743" text="Chorus"/>
            <Component type="ScriptPanel" id="panel_effectTab5" x="387.2999877929688"
                       y="0.0" width="99.0" height="40.0" parentComponent="panel_customizerHeader"
                       allowDragging="1" allowCallbacks="Clicks, Hover &amp; Dragging"
                       itemColour="4278239743" text="Distort"/>
          </Component>
          <Component type="ScriptPanel" id="effectDisplay-Reverb" x="0.0" y="40.0"
                     width="490.0" height="190.0" parentComponent="panel_effectCustomizer"
                     textColour="16777215">
            <Component type="ScriptButton" id="button_smoothing" x="50.0" y="160.0"
                       text="displayButton-SMOOTH" width="70.0" height="30.0" parentComponent="effectDisplay-Reverb"
                       isPluginParameter="1" pluginParameterName="Smooth Ducking"/>
            <Component type="ScriptSlider" id="displayKnob_reverb_feedback" x="140.0"
                       y="50.0" width="70.0" height="110.0" parentComponent="effectDisplay-Reverb"
                       text="FEEDBACK" mode="NormalizedPercentage" suffix="%" middlePosition="0.5"
                       isPluginParameter="1" pluginParameterName="Pre Delay Feedback"
                       enableMidiLearn="0"/>
            <Component type="ScriptSlider" id="displayKnob_reverb_preDelay" x="50.0"
                       y="50.0" width="70.0" height="100.0" text="RELEASE" mode="Time"
                       suffix=" ms" middlePosition="0.5" parentComponent="effectDisplay-Reverb"
                       stepSize="0.001000000047497451" isPluginParameter="1" pluginParameterName="Ducking Release"
                       enableMidiLearn="0"/>
            <Component type="ScriptPanel" id="displayPanel_reverbIndicator" x="3.0"
                       y="0.0" width="480.0" height="4.0" parentComponent="effectDisplay-Reverb"
                       itemColour="4280188415" itemColour2="4280188415" borderSize="1.0"
                       borderRadius="1.0" text="Reverb"/>
            <Component type="ScriptLabel" id="displayLabel_reverb_reverberation" x="360.0"
                       y="20.0" fontName="jetbrains-mono" fontSize="19.0" alignment="left"
                       text="BANDS" width="70.0" height="20.0" parentComponent="effectDisplay-Reverb"
                       editable="0"/>
            <Component type="ScriptLabel" id="displayLabel_Reverb_crossover" x="250.0"
                       y="20.0" text="CROSSOVER" alignment="left" fontSize="19.0" fontName="jetbrains-mono"
                       parentComponent="effectDisplay-Reverb" editable="0" width="110.0"
                       height="20.0"/>
            <Component type="ScriptSlider" id="displayKnob_reverb_hfgain" x="450.0"
                       y="50.0" width="30.0" height="100.0" text="HIGH" parentComponent="effectDisplay-Reverb"
                       mode="NormalizedPercentage" suffix="%" middlePosition="0.5" defaultValue="1.0"/>
            <Component type="ScriptSlider" id="displayKnob_reverb_highcrossover" x="300.0"
                       y="60.0" width="50.0" height="90.0" text="HIGH" parentComponent="effectDisplay-Reverb"
                       mode="Frequency" min="1000.0" max="10000.0" stepSize="1.0" suffix=" Hz"
                       middlePosition="1500.0" isPluginParameter="1" pluginParameterName="Reverb High Crossover"
                       enableMidiLearn="0"/>
            <Component type="ScriptSlider" id="displayKnob_reverb_lowGain" x="370.0"
                       y="50.0" width="30.0" height="100.0" text="LOW" parentComponent="effectDisplay-Reverb"
                       mode="NormalizedPercentage" suffix="%" middlePosition="0.5" defaultValue="1.0"/>
            <Component type="ScriptSlider" id="displayKnob_reverb_lowcrossover" x="250.0"
                       y="60.0" width="50.0" height="90.0" text="LOW " parentComponent="effectDisplay-Reverb"
                       mode="Frequency" min="100.0" max="6000.0" stepSize="1.0" suffix=" Hz"
                       middlePosition="1500.0" isPluginParameter="1" pluginParameterName="Reverb Low Crossover"
                       enableMidiLearn="0"/>
            <Component type="ScriptSlider" id="displayKnob_reverb_midgain" x="410.0"
                       y="50.0" text="MID" width="30.0" height="100.0" parentComponent="effectDisplay-Reverb"
                       mode="NormalizedPercentage" suffix="%" middlePosition="0.5" pluginParameterName="Reverberation Mid"
                       isPluginParameter="1" defaultValue="1.0"/>
            <Component type="ScriptButton" id="displayButton_reverb_panic" x="120.0"
                       y="40.0" parentComponent="effectDisplay-Reverb" width="20.0"
                       height="20.0" text="displayIcon-warning" isMomentary="1" visible="0"/>
            <Component type="ScriptLabel" id="displayLabel_Reverb_ducking" x="50.0"
                       y="20.0" parentComponent="effectDisplay-Reverb" fontName="jetbrains-mono"
                       fontSize="19.0" text="DUCKING" alignment="left" width="70.0"
                       height="20.0" editable="0"/>
            <Component type="ScriptLabel" id="displayLabel_Reverb_preDelayFeedback"
                       x="140.0" y="20.0" parentComponent="effectDisplay-Reverb" width="80.0"
                       height="20.0" text="PRE DELAY" fontName="jetbrains-mono" fontSize="19.0"
                       editable="0"/>
          </Component>
          <Component type="ScriptButton" id="displayButton_reverb_bypass" x="10.0"
                     y="60.0" width="12.0" height="12.0" text="displayIcon-onOff"
                     parentComponent="panel_effectCustomizer" isPluginParameter="1"
                     pluginParameterName="Reverb Bypass"/>
          <Component type="ScriptPanel" id="effectDisplay-Degrade" x="0.0" y="40.0"
                     width="490.0" height="160.0" parentComponent="panel_effectCustomizer"
                     textColour="16777215" visible="0">
            <Component type="ScriptPanel" id="displayPanel_degradeIndicator" x="3.0"
                       y="0.0" width="480.0" height="4.0" parentComponent="effectDisplay-Degrade"
                       itemColour="4294243572" itemColour2="4294243572" borderRadius="1.0"
                       borderSize="1.0" text="Degrade"/>
            <Component type="ScriptSlider" id="displayKnob_degrade_highcut" x="384.0"
                       y="50.0" width="66.0" height="90.0" text="HIGH CUT" parentComponent="effectDisplay-Degrade"
                       mode="Frequency" min="20.0" max="20000.0" stepSize="1.0" suffix=" Hz"
                       middlePosition="1500.0" pluginParameterName="Degrade High Cut"
                       isPluginParameter="1"/>
            <Component type="ScriptSlider" id="displayKnob_degrade_lowcut" x="300.0"
                       y="50.0" text="LOW CUT" width="66.0" height="90.0" parentComponent="effectDisplay-Degrade"
                       mode="Frequency" min="20.0" max="20000.0" stepSize="1.0" suffix=" Hz"
                       middlePosition="1500.0" pluginParameterName="Degrade Low Cut"
                       isPluginParameter="1"/>
            <Component type="ScriptSlider" id="displayKnob_degrade_depth" x="120.0"
                       y="50.0" text="DEPTH" width="72.0" height="102.0" parentComponent="effectDisplay-Degrade"
                       isPluginParameter="1" pluginParameterName="Degrade Mod Depth"/>
            <Component type="ScriptSlider" id="displayKnob_degrade_frequency" x="204.0"
                       y="50.0" text="FREQ" width="72.0" height="102.0" parentComponent="effectDisplay-Degrade"
                       isPluginParameter="1" pluginParameterName="Degrade Mod Frequency"/>
            <Component type="ScriptSlider" id="displayKnob_degrade_amount" x="36.0"
                       y="50.0" text="AMOUNT" width="72.0" height="108.0" parentComponent="effectDisplay-Degrade"
                       max="64.0" isPluginParameter="1" pluginParameterName="Degrade Amount"/>
            <Component type="ScriptLabel" id="displayLabel_degrade_modulation" x="102.0"
                       y="20.0" text="MODULATION" fontSize="19.0" fontName="jetbrains-mono"
                       width="120.0" height="20.0" parentComponent="effectDisplay-Degrade"
                       editable="0"/>
            <Component type="ScriptLabel" id="displayLabel_degrade_filter" x="288.0"
                       y="20.0" text="FILTER" fontSize="19.0" fontName="jetbrains-mono"
                       parentComponent="effectDisplay-Degrade" editable="0" alignment="left"
                       width="76.80000305175781" height="20.0"/>
          </Component>
          <Component type="ScriptButton" id="displayButton_degrade_bypass" x="10.0"
                     y="60.0" text="displayIcon-onOff" width="12.0" height="12.0"
                     parentComponent="panel_effectCustomizer" isPluginParameter="1"
                     pluginParameterName="Degrade Bypass" visible="0"/>
          <Component type="ScriptPanel" id="effectDisplay-Flanger" x="0.0" y="40.0"
                     width="490.0" height="160.0" parentComponent="panel_effectCustomizer"
                     textColour="16777215" visible="0">
            <Component type="ScriptPanel" id="displayPanel_flangerIndicator" x="3.0"
                       y="0.0" width="480.0" height="4.0" parentComponent="effectDisplay-Flanger"
                       itemColour="4284525541" itemColour2="4284525541" borderSize="1.0"
                       borderRadius="1.0" text="Flanger"/>
            <Component type="ScriptSlider" id="displayKnob_flanger_speed" x="36.0" y="50.0"
                       text="SPEED" width="72.0" height="102.0" parentComponent="effectDisplay-Flanger"
                       isPluginParameter="1" pluginParameterName="Flanger Speed"/>
            <Component type="ScriptSlider" id="displayKnob_flanger_depth" x="120.0"
                       y="50.0" text="DEPTH" width="72.0" height="102.0" parentComponent="effectDisplay-Flanger"
                       isPluginParameter="1" pluginParameterName="Flanger Depth"/>
            <Component type="ScriptSlider" id="displayKnob_flanger_feedback" x="204.0"
                       y="50.0" text="FEEDBACK" width="72.0" height="96.0" parentComponent="effectDisplay-Flanger"
                       isPluginParameter="1" pluginParameterName="Flanger Feedback"/>
            <Component type="ScriptSlider" id="displayKnob_flanger_delay" x="300.0"
                       y="50.0" text="DELAY" width="66.0" height="90.0" parentComponent="effectDisplay-Flanger"
                       isPluginParameter="1" pluginParameterName="Flanger Delay"/>
            <Component type="ScriptSlider" id="displayKnob_flanger_offset" x="384.0"
                       y="50.0" text="OFFSET" width="66.0" height="90.0" parentComponent="effectDisplay-Flanger"
                       isPluginParameter="1" pluginParameterName="Flanger Offset"/>
            <Component type="ScriptLabel" id="displayLabel_flanger_controls" x="288.0"
                       y="20.0" text="CONTROLS" fontName="jetbrains-mono" alignment="left"
                       fontSize="19.0" parentComponent="effectDisplay-Flanger" editable="0"
                       width="90.0" height="20.0"/>
          </Component>
          <Component type="ScriptButton" id="displayButton_flanger_bypass" x="10.0"
                     y="60.0" width="12.0" height="12.0" text="displayIcon-onOff"
                     parentComponent="panel_effectCustomizer" isPluginParameter="1"
                     pluginParameterName="Flanger Bypass" visible="0"/>
          <Component type="ScriptPanel" id="effectDisplay-Distort" x="0.0" y="40.0"
                     width="490.0" height="190.0" parentComponent="panel_effectCustomizer"
                     textColour="16777215" visible="0">
            <Component type="ScriptPanel" id="displayPanel_distortIndicator" x="3.0"
                       y="0.0" width="480.0" height="4.0" parentComponent="effectDisplay-Distort"
                       itemColour="4293606219" itemColour2="4293606219" borderSize="1.0"
                       borderRadius="1.0" text="Distort"/>
            <Component type="ScriptSlider" id="displayKnob_distort_lowPass" x="100.0"
                       y="50.0" width="66.0" height="100.0" text="HIGH CUT" parentComponent="effectDisplay-Distort"
                       mode="Frequency" min="20.0" max="20000.0" stepSize="1.0" suffix=" Hz"
                       middlePosition="1500.0"/>
            <Component type="ScriptSlider" id="displayKnob_distort_highpass" x="10.0"
                       y="50.0" width="66.0" height="100.0" text="LOW CUT" parentComponent="effectDisplay-Distort"
                       mode="Frequency" min="20.0" max="20000.0" stepSize="1.0" suffix=" Hz"
                       middlePosition="1500.0"/>
            <Component type="ScriptSlider" id="displayKnob_distort_amount" x="210.0"
                       y="50.0" height="130.0" width="90.0" parentComponent="effectDisplay-Distort"
                       text="AMOUNT" isPluginParameter="1" pluginParameterName="Distortion Amount"/>
            <Component type="ScriptSlider" id="displayKnob_distort_postlowcut" x="420.0"
                       y="50.0" width="66.0" height="100.0" text="HIGH CUT" parentComponent="effectDisplay-Distort"
                       mode="Frequency" min="20.0" max="20000.0" stepSize="1.0" suffix=" Hz"
                       middlePosition="1500.0"/>
            <Component type="ScriptSlider" id="displayKnob_distort_posthighcut" x="330.0"
                       y="50.0" width="66.0" height="100.0" text="LOW CUT" parentComponent="effectDisplay-Distort"
                       mode="Frequency" min="20.0" max="20000.0" stepSize="1.0" suffix=" Hz"
                       middlePosition="1500.0"/>
            <Component type="ScriptLabel" id="disyplayLabel_distort_precut" x="70.0"
                       y="20.0" parentComponent="effectDisplay-Distort" text="PRE CUT"
                       alignment="left" fontName="jetbrains-mono" editable="0" height="20.0"
                       fontSize="19.0"/>
            <Component type="ScriptLabel" id="displayLabel_distort_postcut" x="330.0"
                       y="20.0" text="POST CUT" alignment="left" fontName="jetbrains-mono"
                       editable="0" parentComponent="effectDisplay-Distort" width="120.0"
                       height="20.0" fontSize="19.0"/>
          </Component>
          <Component type="ScriptButton" id="displayButton_distort_bypass" x="10.0"
                     y="60.0" text="displayIcon-onOff" width="12.0" height="12.0"
                     parentComponent="panel_effectCustomizer" isPluginParameter="1"
                     pluginParameterName="Distortion Bypass" visible="0"/>
          <Component type="ScriptPanel" id="effectDisplay-Chorus" x="0.0" y="40.0"
                     width="490.0" height="160.0" parentComponent="panel_effectCustomizer"
                     textColour="16777215" visible="0">
            <Component type="ScriptPanel" id="displayPanel_chorusIndicator" x="3.0"
                       y="0.0" parentComponent="effectDisplay-Chorus" width="480.0"
                       height="4.0" itemColour="4286244807" itemColour2="4286244807"
                       borderRadius="1.0" borderSize="1.0" text="Chorus"/>
            <Component type="ScriptSlider" id="displayKnob_chorus_Delay" x="85.0" y="50.0"
                       text="DELAY" width="66.0" height="90.0" parentComponent="effectDisplay-Chorus"
                       isPluginParameter="1" pluginParameterName="Chorus Delay"/>
            <Component type="ScriptSlider" id="displayKnob_chorus_depth" x="172.0" y="50.0"
                       text="DEPTH" width="66.0" height="90.0" parentComponent="effectDisplay-Chorus"
                       isPluginParameter="1" pluginParameterName="Chorus Depth"/>
            <Component type="ScriptSlider" id="displayKnob_chorus_feedback" x="256.0"
                       y="50.0" text="FEEDBACK" width="66.0" height="90.0" parentComponent="effectDisplay-Chorus"
                       isPluginParameter="1" pluginParameterName="Chorus Feedback" mode="NormalizedPercentage"
                       suffix="%" middlePosition="0.5"/>
            <Component type="ScriptSlider" id="displayKnob_chorus_rate" x="340.0" y="50.0"
                       text="RATE" width="66.0" height="90.0" parentComponent="effectDisplay-Chorus"
                       isPluginParameter="1" pluginParameterName="Chorus Rate"/>
          </Component>
          <Component type="ScriptButton" id="displayButton_chorus_bypass" x="10.0"
                     y="60.0" width="12.0" height="12.0" text="displayIcon-onOff"
                     parentComponent="panel_effectCustomizer" isPluginParameter="1"
                     pluginParameterName="Chorus Bypass" visible="0"/>
        </Component>
      </Component>
      <Component type="ScriptPanel" id="display_filter" x="-2.0" y="8.0" width="500.0"
                 height="240.0" textColour="16777215" parentComponent="panelDisplay_display"
                 bgColour="16777215" visible="0">
        <Component type="ScriptFloatingTile" id="preFilter" x="0.0" y="30.0" width="510.0"
                   height="210.0" ContentType="DraggableFilterPanel" bgColour="11944257"
                   itemColour="2197749760" itemColour2="4294901760" Data="{&#10;  &quot;ProcessorId&quot;: &quot;preFilter&quot;,&#10;  &quot;Index&quot;: -1,&#10;  &quot;FollowWorkspace&quot;: false&#10;}"
                   parentComponent="display_filter" Font="jetbrains-mono" visible="0"/>
        <Component type="ScriptFloatingTile" id="postFilter" x="0.0" y="30.0" width="510.0"
                   height="210.0" parentComponent="display_filter" ContentType="DraggableFilterPanel"
                   bgColour="0" itemColour="2164260863" itemColour2="855638016"
                   Data="{&#10;  &quot;ProcessorId&quot;: &quot;postFilter&quot;,&#10;  &quot;Index&quot;: -1,&#10;  &quot;FollowWorkspace&quot;: false,&#10;  &quot;AllowDynamicSpectrumAnalyser&quot;: 0&#10;}"/>
        <Component type="ScriptButton" id="button_filters_post" x="430.0" y="0.0"
                   width="66.0" height="30.0" text="displayButton-POST" parentComponent="display_filter"
                   saveInPreset="0"/>
        <Component type="ScriptButton" id="button_filters_pre" x="370.0" y="0.0"
                   width="54.0" height="30.0" text="displayButton-PRE" parentComponent="display_filter"
                   saveInPreset="0"/>
      </Component>
      <Component type="ScriptButton" id="button_filter" x="8.0" y="8.0" parentComponent="panelDisplay_display"
                 width="60.0" height="30.0" text="displayButton-EQ" saveInPreset="0"
                 visible="0"/>
      <Component type="ScriptButton" id="button_fx" x="408.0" y="205.0" width="90.0"
                 height="40.0" text="displayButton-EFFECTS" parentComponent="panelDisplay_display"
                 saveInPreset="0"/>
      <Component type="ScriptPanel" id="display_about" x="0.0" y="0.0" width="510.0"
                 height="252.0" parentComponent="panelDisplay_display" itemColour2="4278190080"
                 itemColour="4278190080" visible="0">
        <Component type="ScriptPanel" id="panel_authors" x="78.0" y="138.0" width="360.0"
                   height="90.0" textColour="4294967295" borderRadius="2.0" parentComponent="display_about"/>
        <Component type="ScriptLabel" id="label_name1" x="88.0" y="148.0" width="180.0"
                   height="20.0" text="Oskar Schachtschneider" fontSize="18.0" fontName="jetbrains-mono"
                   parentComponent="display_about" editable="0"/>
        <Component type="ScriptButton" id="button_x1" x="486.0" y="12.0" text="displayIcon-outline-x"
                   itemColour="4294967295" width="12.0" height="12.0" parentComponent="display_about"
                   itemColour2="4222331819" saveInPreset="0" isMomentary="1"/>
        <Component type="ScriptPanel" id="icon_panel_logo" x="238.0" y="28.0" width="48.0"
                   height="48.0" parentComponent="display_about"/>
        <Component type="ScriptPanel" id="panel_message" x="132.0" y="78.0" width="276.0"
                   height="36.0" itemColour2="0" itemColour="0" parentComponent="display_about"
                   textColour="16777215" bgColour="16777215">
          <Component type="ScriptLabel" id="label_in_berlin" x="136.0" y="10.0" text="in Berlin"
                     width="114.0" height="30.0" fontSize="24.0" fontName="jetbrains-mono"
                     parentComponent="panel_message" editable="0"/>
          <Component type="ScriptPanel" id="icon_panel_heart" x="124.0" y="16.0" width="18.0"
                     height="18.0" itemColour="4294932992" itemColour2="4294932992"
                     textColour="4294932992" parentComponent="panel_message"/>
          <Component type="ScriptLabel" id="label_made_in" x="16.0" y="10.0" parentComponent="panel_message"
                     width="108.0" height="30.0" text="Made with" fontSize="24.0"
                     fontName="jetbrains-mono" editable="0"/>
        </Component>
        <Component type="ScriptLabel" id="label_authors" x="84.0" y="120.0" parentComponent="display_about"
                   text="AUTHORS:" alignment="left" fontSize="18.0" fontName="jetbrains-mono"
                   editable="0" width="76.80000305175781" height="16.79999923706055"/>
      </Component>
      <Component type="ScriptPanel" id="display_settings" x="0.0" y="0.0" width="510.0"
                 height="252.0" parentComponent="panelDisplay_display" itemColour2="4278190080"
                 itemColour="4278190080" textColour="16777215" visible="0">
        <Component type="ScriptPanel" id="panel_settings_container" x="-2.0" y="-2.0"
                   width="190.0" height="190.0" parentComponent="display_settings"
                   textColour="16777215">
          <Component type="ScriptButton" id="button_settings_general" x="10.0" y="10.0"
                     parentComponent="panel_settings_container" width="180.0" height="40.0"
                     text="displayButton-GENERAL" itemColour="4288782753" bgColour="4278190080"
                     itemColour2="65386" saveInPreset="0" enableMidiLearn="0"/>
          <Component type="ScriptButton" id="button_settings_activate" x="10.0" y="55.0"
                     parentComponent="panel_settings_container" width="180.0" height="40.0"
                     text="displayButton-ACTIVATE" saveInPreset="0" bgColour="4278190080"
                     itemColour="4288782753" itemColour2="1118481" enableMidiLearn="0"/>
          <Component type="ScriptButton" id="button_settings_about" x="10.0" y="100.0"
                     parentComponent="panel_settings_container" width="180.0" height="40.0"
                     text="displayButton-ABOUT" saveInPreset="0" itemColour="4288782753"
                     bgColour="4278190080" itemColour2="1118481" enableMidiLearn="0"/>
        </Component>
        <Component type="ScriptButton" id="button_buy_reach" x="8.0" y="198.0" width="180.0"
                   height="50.0" text="displayButton-Buy REACH" parentComponent="display_settings"
                   bgColour="4294967295" textColour="4278190080" itemColour="4292532954"
                   isMomentary="1" saveInPreset="0" defaultValue="1.0" enableMidiLearn="0"
                   visible="0"/>
        <Component type="ScriptPanel" id="panel_settings_content_container" x="178.0"
                   y="-2.0" width="340.0" height="260.0" parentComponent="display_settings"
                   bgColour="16777215" itemColour="0" itemColour2="0" textColour="16777215">
          <Component type="ScriptPanel" id="dis-settings_general" x="20.0" y="30.0"
                     width="300.0" height="210.0" parentComponent="panel_settings_content_container"
                     itemColour="0" itemColour2="0" bgColour="16777215" textColour="16777215"
                     visible="0">
            <Component type="ScriptLabel" id="label_theme" x="0.0" y="62.0" fontSize="19.0"
                       fontName="jetbrains-mono" text="THEME" alignment="left" parentComponent="dis-settings_general"
                       width="70.0" height="40.0"/>
            <Component type="ScriptComboBox" id="ComboBox_theme" x="160.0" y="62.0"
                       max="2" width="120.0" height="40.0" items="Light&#10;Dark" text="Light"
                       saveInPreset="0" parentComponent="dis-settings_general"/>
            <Component type="ScriptLabel" id="UI Zoom Factor" x="0.0" y="12.0" fontSize="19.0"
                       fontName="jetbrains-mono" alignment="left" width="130.0" height="40.0"
                       parentComponent="dis-settings_general" text="SCALING"/>
            <Component type="ScriptComboBox" id="ComboBox_zoom" x="160.0" y="10.0" max="13"
                       width="120.0" height="40.0" items="30%&#10;40%&#10;50%&#10;60%&#10;75%&#10;100%&#10;125%&#10;150%&#10;175%&#10;200%&#10;250%&#10;300%&#10;Custom"
                       text="" parentComponent="dis-settings_general" saveInPreset="0"/>
            <Component type="ScriptLabel" id="label_settings_animation" x="0.0" y="112.0"
                       width="140.0" height="40.0" text="ANIMATIONS" fontSize="19.0"
                       fontName="jetbrains-mono" alignment="left" parentComponent="dis-settings_general"
                       editable="0"/>
            <Component type="ScriptButton" id="button_animationToggle" x="210.0" y="112.0"
                       height="40.0" text="switch" bgColour="3506438143" textColour="16777215"
                       itemColour2="1118481" width="70.0" saveInPreset="0" parentComponent="dis-settings_general"
                       defaultValue="1.0"/>
            <Component type="ScriptButton" id="button_startupAnimationToggle" x="210.0"
                       y="162.0" width="70.0" height="40.0" text="switch" parentComponent="dis-settings_general"
                       saveInPreset="0" defaultValue="1.0"/>
            <Component type="ScriptLabel" id="label_settings_startupAnimation" x="0.0"
                       y="162.0" width="140.0" height="40.0" text="SPLASH SCREEN" fontName="jetbrains-mono"
                       fontSize="19.0" alignment="left" parentComponent="dis-settings_general"/>
          </Component>
          <Component type="ScriptPanel" id="dis-settings_activate" x="0.0" y="0.0"
                     width="340.0" height="260.0" parentComponent="panel_settings_content_container"
                     textColour="0" itemColour2="0" itemColour="0" bgColour="0">
            <Component type="ScriptPanel" id="displayPanel_login" x="6.0" y="0.0" width="330.0"
                       height="260.0" itemColour="0" itemColour2="0" parentComponent="dis-settings_activate"
                       borderSize="0.0" visible="0">
              <Component type="ScriptPanel" id="Panel1" x="44.0" y="85.0" textColour="4294967295"
                         width="250.0" height="40.0" borderRadius="1.0" borderSize="1.0"
                         parentComponent="displayPanel_login">
                <Component type="ScriptLabel" id="label_email" x="0.0" y="0.0" width="250.0"
                           height="40.0" fontSize="26.0" fontName="jetbrains-mono" alignment="left"
                           text="" parentComponent="Panel1"/>
              </Component>
              <Component type="ScriptLabel" id="displayLabel_password" x="40.0" y="130.0"
                         text="PASSWORD" fontName="jetbrains-mono" fontSize="18.0" alignment="left"
                         parentComponent="displayPanel_login" editable="0" width="110.0"
                         height="30.0"/>
              <Component type="ScriptLabel" id="label_license_code" x="40.0" y="55.0"
                         text="EMAIL / USERNAME" fontName="jetbrains-mono" fontSize="18.0"
                         width="210.0" height="30.0" parentComponent="displayPanel_login"
                         editable="0" alignment="left"/>
              <Component type="ScriptPanel" id="panel_license_input" x="44.0" y="160.0"
                         width="250.0" height="40.0" borderSize="1.0" borderRadius="1.0"
                         textColour="4294967295" parentComponent="displayPanel_login">
                <Component type="ScriptLabel" id="label_password" x="0.0" y="0.0" width="250.0"
                           height="40.0" fontName="space" fontSize="34.0" alignment="left"
                           text="" parentComponent="panel_license_input" fontStyle="Password"/>
              </Component>
              <Component type="ScriptButton" id="button_activate" x="44.0" y="210.0" width="250.0"
                         height="40.0" text="ACTIVATE" parentComponent="displayPanel_login"
                         itemColour="4292532954" textColour="4278190080" isMomentary="1"
                         bgColour="4294967295" itemColour2="4227792896" saveInPreset="0"
                         defaultValue="1.0" enableMidiLearn="0"/>
              <Component type="ScriptLabel" id="label_not_found" x="-6.0" y="120.0" parentComponent="displayPanel_login"
                         fontSize="20.0" fontName="space" textColour="4294927974" text="Credentials are incorrect."
                         width="300.0" height="30.0" editable="0" visible="0"/>
            </Component>
            <Component type="ScriptLabel" id="label_thank_you" x="50.0" y="110.0" text="Thank you for using REACH"
                       fontName="jetbrains-mono" width="240.0" height="30.0" fontSize="20.0"
                       parentComponent="dis-settings_activate" editable="0"/>
            <Component type="ScriptPanel" id="displayPanel_serial" x="10.0" y="0.0"
                       width="330.0" height="260.0" parentComponent="dis-settings_activate"
                       itemColour="16711680" itemColour2="0" bgColour="16777215">
              <Component type="ScriptPanel" id="Panel2" x="40.0" y="100.0" width="240.0"
                         height="40.0" textColour="4294967295" borderRadius="1.0" borderSize="1.0"
                         itemColour2="0" itemColour="0" parentComponent="displayPanel_serial"/>
              <Component type="ScriptButton" id="displayButton_activateSerial" x="40.0"
                         y="150.0" width="240.0" height="40.0" text="ACTIVATE" parentComponent="displayPanel_serial"
                         saveInPreset="0"/>
              <Component type="ScriptLabel" id="displayLabel_serialKey" x="40.0" y="100.0"
                         width="240.0" height="40.0" fontSize="22.0" fontName="jetbrains-mono"
                         alignment="left" parentComponent="displayPanel_serial" text=""/>
              <Component type="ScriptLabel" id="displayLabel_serial" x="35.0" y="70.0"
                         text="SERIAL" fontName="jetbrains-mono" fontSize="18.0" alignment="left"
                         parentComponent="displayPanel_serial" editable="0"/>
            </Component>
            <Component type="ScriptButton" id="displayButton_serial" x="50.0" y="10.0"
                       width="100.0" height="40.0" parentComponent="dis-settings_activate"
                       text="displayButton-SERIAL" saveInPreset="0"/>
            <Component type="ScriptButton" id="displayButton_login" x="160.0" y="10.0"
                       parentComponent="dis-settings_activate" text="displayButton-LOGIN"
                       width="100.0" height="40.0" saveInPreset="0"/>
          </Component>
          <Component type="ScriptPanel" id="dis-settings_about" x="0.0" y="0.0" width="330.0"
                     height="250.0" parentComponent="panel_settings_content_container"
                     textColour="0" itemColour2="0" itemColour="0" bgColour="0" visible="0">
            <Component type="ScriptButton" id="button_website" x="200.0" y="200.0" text="displayButton-Website"
                       width="120.0" height="40.0" bgColour="4294967295" itemColour="4292532954"
                       parentComponent="dis-settings_about" itemColour2="4227858431"
                       textColour="4278190080" isMomentary="1" saveInPreset="0"/>
            <Component type="ScriptPanel" id="icon_panel_fullLogo" x="50.0" y="70.0"
                       width="220.0" height="30.0" bgColour="4294967295" parentComponent="dis-settings_about"/>
            <Component type="ScriptLabel" id="label_aboutTitle" x="110.0" y="118.0"
                       fontSize="20.0" fontName="space" text="Reach" parentComponent="dis-settings_about"
                       editable="0" width="76.80000305175781" height="16.79999923706055"/>
            <Component type="ScriptLabel" id="label_version" x="98.0" y="136.0" text="Version: 1.3"
                       locked="1" fontName="space" fontSize="20.0" width="102.0" height="18.0"
                       parentComponent="dis-settings_about" editable="0"/>
          </Component>
          <Component type="ScriptPanel" id="dis-settings_audio" x="0.0" y="0.0" width="300.0"
                     height="186.0" parentComponent="panel_settings_content_container"
                     visible="0">
            <Component type="ScriptFloatingTile" id="FloatingTile3" x="0.0" y="0.0"
                       width="300.0" height="186.0" ContentType="CustomSettings" bgColour="4278190080"
                       itemColour="0" itemColour2="0" Data="{&#10;  &quot;Driver&quot;: true,&#10;  &quot;Device&quot;: true,&#10;  &quot;Output&quot;: true,&#10;  &quot;BufferSize&quot;: true,&#10;  &quot;SampleRate&quot;: false,&#10;  &quot;GlobalBPM&quot;: true,&#10;  &quot;StreamingMode&quot;: false,&#10;  &quot;ScaleFactor&quot;: false,&#10;  &quot;VoiceAmountMultiplier&quot;: false,&#10;  &quot;ClearMidiCC&quot;: false,&#10;  &quot;SampleLocation&quot;: false,&#10;  &quot;DebugMode&quot;: false,&#10;  &quot;UseOpenGL&quot;: false,&#10;  &quot;ScaleFactorList&quot;: [&#10;    0.5,&#10;    0.75,&#10;    1.0,&#10;    1.25,&#10;    1.5,&#10;    2.0&#10;  ]&#10;}"
                       FontSize="32.0" parentComponent="dis-settings_audio" Font="space"/>
          </Component>
        </Component>
        <Component type="ScriptButton" id="button_x2" x="486.0" y="12.0" width="12.0"
                   height="12.0" text="displayIcon-outline-x" itemColour="4294967295"
                   parentComponent="display_settings" itemColour2="4222331819" saveInPreset="0"
                   isMomentary="1"/>
      </Component>
      <Component type="ScriptPanel" id="display_presetBrowser" x="0.0" y="0.0"
                 width="510.0" height="252.0" parentComponent="panelDisplay_display"
                 itemColour="4278779904" itemColour2="4278190080" textColour="16777215"
                 bgColour="16777215" visible="0">
        <Component type="ScriptFloatingTile" id="FloatingTile2" x="-2.0" y="-2.0"
                   width="520.0" height="260.0" ContentType="PresetBrowser" bgColour="4278190080"
                   itemColour="4294967295" itemColour2="0" Data="{&#10;  &quot;ShowSaveButton&quot;: true,&#10;  &quot;ShowExpansionsAsColumn&quot;: false,&#10;  &quot;ShowFolderButton&quot;: true,&#10;  &quot;ShowNotes&quot;: false,&#10;  &quot;ShowEditButtons&quot;: true,&#10;  &quot;EditButtonOffset&quot;: 2,&#10;  &quot;ShowAddButton&quot;: true,&#10;  &quot;ShowRenameButton&quot;: true,&#10;  &quot;ShowDeleteButton&quot;: true,&#10;  &quot;ShowFavoriteIcon&quot;: false,&#10;  &quot;ButtonsInsideBorder&quot;: false,&#10;  &quot;NumColumns&quot;: 2,&#10;  &quot;ColumnWidthRatio&quot;: [&#10;    0.3333333333333333,&#10;    0.6333333333333333&#10;  ],&#10;  &quot;ListAreaOffset&quot;: [&#10;    -5,&#10;    -5,&#10;    10,&#10;    15&#10;  ],&#10;  &quot;ColumnRowPadding&quot;: [&#10;    10,&#10;    10,&#10;    5,&#10;    10&#10;  ],&#10;  &quot;SearchBarBounds&quot;: [&#10;    0,&#10;    0,&#10;    0,&#10;    0&#10;  ],&#10;  &quot;MoreButtonBounds&quot;: [&#10;    0,&#10;    5,&#10;    25,&#10;    23&#10;  ],&#10;  &quot;SaveButtonBounds&quot;: [&#10;    50,&#10;    5,&#10;    300,&#10;    23&#10;  ],&#10;  &quot;FavoriteButtonBounds&quot;: []&#10;}"
                   Font="space" parentComponent="display_presetBrowser" itemColour3="4278190080"/>
        <Component type="ScriptButton" id="button_x3" x="486.0" y="12.0" width="12.0"
                   height="12.0" text="displayIcon-outline-x" itemColour="4294967295"
                   parentComponent="display_presetBrowser" itemColour2="4222331819"
                   saveInPreset="0" isMomentary="1"/>
      </Component>
    </Component>
  </Component>
  <Component type="ScriptPanel" id="ZoomPanel" x="1110.0" y="490.0" width="25.0"
             height="20.0" allowCallbacks="Clicks, Hover &amp; Dragging"/>
  <Component type="ScriptPanel" id="animationBackground" x="310.0" y="70.0"
             width="510.0" height="250.0" itemColour="4278190080" itemColour2="4278190080"
             textColour="16777215" visible="0">
    <Component type="ScriptPanel" id="tubeAni" x="190.0" y="50.0" width="130.0"
               height="130.0" parentComponent="animationBackground" visible="0"/>
  </Component>
</ContentProperties>
